LICENSE
MANIFEST.in
README.rst
requirements.txt
setup.py
test-requirements.txt
gotland/__init__.py
gotland.egg-info/PKG-INFO
gotland.egg-info/SOURCES.txt
gotland.egg-info/dependency_links.txt
gotland.egg-info/requires.txt
gotland.egg-info/top_level.txt
gotland.egg-info/zip-safe
gotland/rabbit/__init__.py
gotland/rabbit/api.py
tests/__init__.py
tests/__init__.pyc
tests/apitest.py
tests/apitest.pyc
tests/__pycache__/__init__.cpython-33.pyc
tests/__pycache__/apitest.cpython-33.pyc
tests/fixtures/test_aliveness.yaml
tests/fixtures/test_aliveness_fails.yaml
tests/fixtures/test_create_user.yaml
tests/fixtures/test_delete_user.yaml
tests/fixtures/test_get_bindings.yaml
tests/fixtures/test_get_bindings_by_queue.yaml
tests/fixtures/test_get_bindings_by_vhost.yaml
tests/fixtures/test_get_bindings_for_exchange.yaml
tests/fixtures/test_get_channels.yaml
tests/fixtures/test_get_channels_name.yaml
tests/fixtures/test_get_connections.yaml
tests/fixtures/test_get_connections_name.yaml
tests/fixtures/test_get_exchanges.yaml
tests/fixtures/test_get_exchanges_by_vhost.yaml
tests/fixtures/test_get_exchanges_name_vhost.yaml
tests/fixtures/test_get_extensions.yaml
tests/fixtures/test_get_node_info.yaml
tests/fixtures/test_get_nodes.yaml
tests/fixtures/test_get_queue_by_name.yaml
tests/fixtures/test_get_queues.yaml
tests/fixtures/test_get_queues_by_vhost.yaml
tests/fixtures/test_overview.yaml
tests/fixtures/test_overview_for_content.yaml